[
  {
    "Id": 1,
    "userId": "1",
    "fullName": "John Doe",
    "phone": "+1234567890",
    "location": "San Francisco, CA",
    "resumeUrl": "/resumes/john-doe.pdf",
    "skills": ["JavaScript", "React", "Node.js", "TypeScript", "AWS"],
    "experience": [
      {
        "title": "Senior Frontend Developer",
        "company": "Tech Solutions Inc",
        "duration": "2020 - Present",
        "description": "Leading frontend development for enterprise applications"
      },
      {
        "title": "Frontend Developer",
        "company": "StartupXYZ",
        "duration": "2018 - 2020",
        "description": "Developed responsive web applications using React"
      }
    ],
    "education": [
      {
        "degree": "Bachelor of Science in Computer Science",
        "institution": "Stanford University",
        "year": "2018"
      }
    ],
    "totalExperienceYears": 6
  },
  {
    "Id": 2,
    "userId": "4",
    "fullName": "Sarah Wilson",
    "phone": "+1234567891",
    "location": "New York, NY",
    "resumeUrl": "/resumes/sarah-wilson.pdf",
    "skills": ["Python", "Django", "PostgreSQL", "Docker", "AWS"],
    "experience": [
      {
        "title": "Backend Engineer",
        "company": "DataFlow Corp",
        "duration": "2019 - Present",
        "description": "Building scalable backend systems and APIs"
      }
    ],
    "education": [
      {
        "degree": "Master of Science in Software Engineering",
        "institution": "MIT",
        "year": "2019"
      }
    ],
    "totalExperienceYears": 5
  },
  {
    "Id": 3,
    "userId": "6",
    "fullName": "Alex Chen",
    "phone": "+1234567892",
    "location": "Austin, TX",
    "resumeUrl": "/resumes/alex-chen.pdf",
    "skills": ["Java", "Spring Boot", "Microservices", "Kubernetes", "MongoDB"],
    "experience": [
      {
        "title": "Software Engineer",
        "company": "Enterprise Solutions",
        "duration": "2021 - Present",
        "description": "Developing enterprise-grade microservices"
      }
    ],
    "education": [
      {
        "degree": "Bachelor of Science in Software Engineering",
        "institution": "University of Texas",
        "year": "2021"
      }
    ],
    "totalExperienceYears": 3
  },
  {
    "Id": 4,
    "userId": "8",
    "fullName": "David Kim",
    "phone": "+1234567893",
    "location": "Seattle, WA",
    "resumeUrl": "/resumes/david-kim.pdf",
    "skills": ["UI/UX Design", "Figma", "Adobe XD", "HTML", "CSS"],
    "experience": [
      {
        "title": "UI/UX Designer",
        "company": "Design Studio",
        "duration": "2020 - Present",
        "description": "Creating user-centered design solutions"
      }
    ],
    "education": [
      {
        "degree": "Bachelor of Fine Arts in Design",
        "institution": "Rhode Island School of Design",
        "year": "2020"
      }
    ],
    "totalExperienceYears": 4
  }
]